{
  "nodes": [
    {
      "id": 1,
      "name": "Home",
      "desc": "Page d'accueil",
      "x": 300,
      "y": 100
    },
    {
      "id": 1767783816766,
      "name": "Nouvelle Page",
      "desc": "",
      "x": 199.02173103135232,
      "y": 283.3064661897346
    },
    {
      "id": 1767783817183,
      "name": "Nouvelle Page",
      "desc": "",
      "x": 448.6917951983405,
      "y": 320.388969330188
    }
  ],
  "links": [
    {
      "from": 1767783816766,
      "to": 1
    },
    {
      "from": 1,
      "to": 1767783817183
    }
  ],
  "title": "ProjetTest"
}